[{"timeSeconds":0.009999999776482582,"markName":"0"},
{"timeSeconds":6.849874019622803,"markName":"1"},
{"timeSeconds":13.605709075927734,"markName":"2"},
{"timeSeconds":21.7396240234375,"markName":"3"},
{"timeSeconds":34.14154052734375,"markName":"4"},
{"timeSeconds":43.758541107177734,"markName":"5"},
{"timeSeconds":47.127498626708984,"markName":"6"},
{"timeSeconds":56.349246978759766,"markName":"7"},
{"timeSeconds":61.04912185668945,"markName":"8"},
{"timeSeconds":66.830078125,"markName":"9"},
{"timeSeconds":72.57412719726562,"markName":"10"},
{"timeSeconds":76.18258666992188,"markName":"11"},
{"timeSeconds":82.17129516601562,"markName":"12"},
{"timeSeconds":88.12767028808594,"markName":"13"},
{"timeSeconds":96.16708374023438,"markName":"14"},
{"timeSeconds":107.13195037841797,"markName":"15"},
{"timeSeconds":113.44261932373047,"markName":"16"},
{"timeSeconds":115.92474365234375,"markName":"17"},
{"timeSeconds":120.65995025634766,"markName":"18"},
{"timeSeconds":127.76011657714844,"markName":"19"},
{"timeSeconds":130.59886169433594,"markName":"20"},
{"timeSeconds":134.39056396484375,"markName":"21"},
{"timeSeconds":137.671,"markName":"22"},
{"timeSeconds":140.42330932617188,"markName":"23"},
{"timeSeconds":148.57640075683594,"markName":"24"},
{"timeSeconds":154.1775665283203,"markName":"25"},
{"timeSeconds":158.128,"markName":"26"},
{"timeSeconds":165.37173461914062,"markName":"27"},
{"timeSeconds":177.22015380859375,"markName":"28"},
{"timeSeconds":184.580322265625,"markName":"29"},
{"timeSeconds":196.14183044433594,"markName":"30"},
{"timeSeconds":205.05308532714844,"markName":"31"},
{"timeSeconds":209.15049743652344,"markName":"32"},
{"timeSeconds":215.00045776367188,"markName":"33"},
{"timeSeconds":225.21221923828125,"markName":"34"},
{"timeSeconds":227.9333953857422,"markName":"35"},
{"timeSeconds":238.0448760986328,"markName":"36"},
{"timeSeconds":244.3868865966797,"markName":"37"},
{"timeSeconds":251.32997131347656,"markName":"38"}]
